torc/__init__.py
torc/api.py
torc/async_cli_command.py
torc/common.py
torc/config.py
torc/exceptions.py
torc/job_runner.py
torc/loggers.py
torc/py.typed
torc/resource_monitor_reports.py
torc/workflow_manager.py
torc/apps/__init__.py
torc/apps/management_console.py
torc/apps/management_console.tcss
torc/cli/__init__.py
torc/cli/collections.py
torc/cli/common.py
torc/cli/compute_nodes.py
torc/cli/config.py
torc/cli/events.py
torc/cli/export.py
torc/cli/files.py
torc/cli/graphs.py
torc/cli/hpc.py
torc/cli/jobs.py
torc/cli/reports.py
torc/cli/resource_requirements.py
torc/cli/results.py
torc/cli/run_function.py
torc/cli/run_postprocess.py
torc/cli/slurm.py
torc/cli/stats.py
torc/cli/torc.py
torc/cli/tui.py
torc/cli/user_data.py
torc/cli/workflows.py
torc/hpc/__init__.py
torc/hpc/common.py
torc/hpc/hpc_interface.py
torc/hpc/hpc_manager.py
torc/hpc/slurm_interface.py
torc/openapi_client/__init__.py
torc/openapi_client/api_client.py
torc/openapi_client/api_response.py
torc/openapi_client/configuration.py
torc/openapi_client/exceptions.py
torc/openapi_client/py.typed
torc/openapi_client/rest.py
torc/openapi_client/api/__init__.py
torc/openapi_client/api/default_api.py
torc/openapi_client/models/__init__.py
torc/openapi_client/models/add_jobs_response.py
torc/openapi_client/models/auto_tune_status.py
torc/openapi_client/models/aws_scheduler_model.py
torc/openapi_client/models/compute_node_model.py
torc/openapi_client/models/compute_node_resource_stats_model.py
torc/openapi_client/models/compute_node_schedule_params.py
torc/openapi_client/models/compute_node_stats.py
torc/openapi_client/models/compute_node_stats_model.py
torc/openapi_client/models/compute_nodes_resources.py
torc/openapi_client/models/default_error_response.py
torc/openapi_client/models/edge_model.py
torc/openapi_client/models/file_model.py
torc/openapi_client/models/get_dot_graph_response.py
torc/openapi_client/models/get_ready_job_requirements_response.py
torc/openapi_client/models/is_complete_response.py
torc_client-0.6.4.dist-info/METADATA
torc_client-0.6.4.dist-info/WHEEL
torc_client-0.6.4.dist-info/entry_points.txt
torc_client-0.6.4.dist-info/top_level.txt
torc_client-0.6.4.dist-info/RECORD
