Metadata-Version: 2.4
Name: torc-client
Version: 0.6.4
Summary: Workflow management system
Author-email: Daniel Thom <daniel.thom@nrel.gov>, Joseph McKinsey <joseph.mckinsey@nrel.gov>
License-Expression: BSD-3-Clause
Keywords: hpc,workflow,pipeline
Classifier: Development Status :: 4 - Beta
Classifier: Natural Language :: English
Classifier: Programming Language :: Python :: 3.12
Requires-Python: <3.14,>=3.11
Requires-Dist: click<9,>=8.2
Requires-Dist: dynaconf
Requires-Dist: graphviz
Requires-Dist: json5
Requires-Dist: isodate
Requires-Dist: loguru
Requires-Dist: plotly<6,>=5.19
Requires-Dist: psutil<6,>=5.9
Requires-Dist: prettytable<4,>=3.10
Requires-Dist: pydantic<3,>=2.10
Requires-Dist: py-libnuma
Requires-Dist: rmon
Requires-Dist: rich
Requires-Dist: rich_click
Requires-Dist: textual<4,>=3.2
Requires-Dist: toml
Requires-Dist: urllib3<3.0.0,>=2.1.0
Requires-Dist: python-dateutil>=2.8.2
Requires-Dist: typing-extensions>=4.7.1
Provides-Extra: dev
Requires-Dist: black; extra == "dev"
Requires-Dist: bump-my-version; extra == "dev"
Requires-Dist: filelock; extra == "dev"
Requires-Dist: flake8; extra == "dev"
Requires-Dist: furo; extra == "dev"
Requires-Dist: ghp-import; extra == "dev"
Requires-Dist: mypy; extra == "dev"
Requires-Dist: myst_parser; extra == "dev"
Requires-Dist: pre-commit; extra == "dev"
Requires-Dist: pytest; extra == "dev"
Requires-Dist: pytest-cov; extra == "dev"
Requires-Dist: ruff; extra == "dev"
Requires-Dist: sphinx; extra == "dev"
Requires-Dist: sphinx-click; extra == "dev"
Requires-Dist: sphinxcontrib-openapi; extra == "dev"
Requires-Dist: autodoc_pydantic~=2.0; extra == "dev"
Requires-Dist: sphinx-copybutton; extra == "dev"
Requires-Dist: sphinx-tabs~=3.4; extra == "dev"
Requires-Dist: textual-dev; extra == "dev"
Requires-Dist: types-networkx; extra == "dev"
Requires-Dist: types-python-dateutil; extra == "dev"
Requires-Dist: types-psutil; extra == "dev"
Requires-Dist: types-toml; extra == "dev"
Provides-Extra: plots
Requires-Dist: networkx; extra == "plots"
Requires-Dist: networkxgmml; extra == "plots"
Requires-Dist: pygraphviz; extra == "plots"
